odoo10_addon_website_signup_legal_page_required-10.0.1.0.0.99.dev5-py3.8-nspkg.pth
odoo/addons/website_signup_legal_page_required/README.rst
odoo/addons/website_signup_legal_page_required/__init__.py
odoo/addons/website_signup_legal_page_required/__manifest__.py
odoo/addons/website_signup_legal_page_required/controllers/__init__.py
odoo/addons/website_signup_legal_page_required/controllers/exceptions.py
odoo/addons/website_signup_legal_page_required/controllers/main.py
odoo/addons/website_signup_legal_page_required/i18n/ca.po
odoo/addons/website_signup_legal_page_required/i18n/de.po
odoo/addons/website_signup_legal_page_required/i18n/el_GR.po
odoo/addons/website_signup_legal_page_required/i18n/es.po
odoo/addons/website_signup_legal_page_required/i18n/fi.po
odoo/addons/website_signup_legal_page_required/i18n/fr.po
odoo/addons/website_signup_legal_page_required/i18n/hr_HR.po
odoo/addons/website_signup_legal_page_required/i18n/it.po
odoo/addons/website_signup_legal_page_required/i18n/pt_BR.po
odoo/addons/website_signup_legal_page_required/i18n/ru.po
odoo/addons/website_signup_legal_page_required/i18n/sl.po
odoo/addons/website_signup_legal_page_required/i18n/website_legal_page_required.pot
odoo/addons/website_signup_legal_page_required/i18n/website_signup_legal_page_required.pot
odoo/addons/website_signup_legal_page_required/models/__init__.py
odoo/addons/website_signup_legal_page_required/models/res_users.py
odoo/addons/website_signup_legal_page_required/static/description/icon.png
odoo/addons/website_signup_legal_page_required/views/pages.xml
odoo/addons/website_signup_legal_page_required/views/res_users.xml
odoo10_addon_website_signup_legal_page_required-10.0.1.0.0.99.dev5.dist-info/METADATA
odoo10_addon_website_signup_legal_page_required-10.0.1.0.0.99.dev5.dist-info/WHEEL
odoo10_addon_website_signup_legal_page_required-10.0.1.0.0.99.dev5.dist-info/namespace_packages.txt
odoo10_addon_website_signup_legal_page_required-10.0.1.0.0.99.dev5.dist-info/top_level.txt
odoo10_addon_website_signup_legal_page_required-10.0.1.0.0.99.dev5.dist-info/RECORD
